{"1":[{"name":"标题","uid":"12432445425","content":"这里是内容"},{"name":"anonymous","content":"","uid":"7442014768511869"},{"name":"anonymous","content":"","uid":"2939016850225129"},{"name":"anonymous","content":"","uid":"7024504143620858"},{"name":"anonymous","content":"你好","uid":"47593830112750335"},{"name":"anonymous","content":"efwefwe","uid":"05129370302231728"}],"魏征":[{"name":"anonymous","content":"魏徵，现作“魏征”（北周大象二年（580年）－唐贞观十七年（643年2月11日）），","uid":"25142804752465353"}],"卢照邻":[{"name":"anonymous","content":"卢照邻（约635-约685年），字升之，号幽忧子，幽州范阳（今河北涿州市）人。","uid":"24779283976330158"}],"-1":[{"name":"anonymous","content":"hello","uid":"9160033603140056"}],"玄奘西行":[{"name":"anonymous","content":"629年，玄奘毅然由长安私发，冒险前往天竺。","uid":"10879999129391948"}],"白居易":[{"name":"anonymous","content":"123","uid":"02419217729863199"},{"name":"anonymous","content":"23","uid":"6651778506146644"},{"name":"anonymous","content":"帅！","uid":"7596902410746234"}],"霍去病":[{"name":"anonymous","content":"00","uid":"27368380167752515"},{"name":"anonymous","content":"00","uid":"42067966600374773"}]}